interscript/__init__.py
interscript/functions.py
interscript/interscript.py
interscript/stdlib.py
interscript/maps/acadsin-zho-Hani-Latn-2002.py
interscript/maps/alalc-amh-Ethi-Latn-1997.py
interscript/maps/alalc-amh-Ethi-Latn-2011.py
interscript/maps/alalc-ara-Arab-Latn-1997.py
interscript/maps/alalc-asm-Deva-Latn-1997.py
interscript/maps/alalc-asm-Deva-Latn-2012.py
interscript/maps/alalc-aze-Arab-Latn-1997.py
interscript/maps/alalc-aze-Cyrl-Latn-1997.py
interscript/maps/alalc-bel-Cyrl-Latn-1997.py
interscript/maps/alalc-ben-Beng-Latn-1997.py
interscript/maps/alalc-ben-Beng-Latn-2017.py
interscript/maps/alalc-bul-Cyrl-Latn-1997.py
interscript/maps/alalc-div-Thaa-Latn-1997.py
interscript/maps/alalc-div-Thaa-Latn-2012.py
interscript/maps/alalc-ell-Grek-Latn-1997.py
interscript/maps/alalc-ell-Grek-Latn-2010.py
interscript/maps/alalc-fas-Arab-Latn-1997.py
interscript/maps/alalc-guj-Gujr-Latn-1997.py
interscript/maps/alalc-guj-Gujr-Latn-2011.py
interscript/maps/alalc-hin-Deva-Latn-1997.py
interscript/maps/alalc-hin-Deva-Latn-2011.py
interscript/maps/alalc-kan-Kana-Latn-1997.py
interscript/maps/alalc-kan-Kana-Latn-2011.py
interscript/maps/alalc-kat-Geok-Latn-1997.py
interscript/maps/alalc-kat-Geok-Latn-2011.py
interscript/maps/alalc-kat-Geor-Latn-1997.py
interscript/maps/alalc-kat-Geor-Latn-2011.py
interscript/maps/alalc-kor-Hang-Latn-1997.py
interscript/maps/alalc-mal-Mlym-Latn-1997.py
interscript/maps/alalc-mal-Mlym-Latn-2012.py
interscript/maps/alalc-mar-Deva-Latn-1997.py
interscript/maps/alalc-mar-Deva-Latn-2011.py
interscript/maps/alalc-mkd-Cyrl-Latn-1997.py
interscript/maps/alalc-mkd-Cyrl-Latn-2013.py
interscript/maps/alalc-mon-Cyrl-Latn-1997.py
interscript/maps/alalc-ori-Orya-Latn-1997.py
interscript/maps/alalc-ori-Orya-Latn-2011.py
interscript/maps/alalc-pan-Guru-Latn-1997.py
interscript/maps/alalc-pan-Guru-Latn-2011.py
interscript/maps/alalc-pli-Deva-Latn-2012.py
interscript/maps/alalc-pra-Deva-Latn-2012.py
interscript/maps/alalc-rus-Cyrl-Latn-1997.py
interscript-0.1.0.dist-info/LICENSE.adoc
interscript-0.1.0.dist-info/METADATA
interscript-0.1.0.dist-info/WHEEL
interscript-0.1.0.dist-info/top_level.txt
interscript-0.1.0.dist-info/RECORD
