Metadata-Version: 2.1
Name: interscript
Version: 0.1.0
Summary: Interoperable script conversion systems
Author-email: "Ribose Inc." <open.source@ribose.com>
Project-URL: Homepage, https://www.interscript.org
Project-URL: Issues, https://github.com/interscript/interscript-python/issues
Classifier: Programming Language :: Python :: 3
Classifier: License :: OSI Approved :: BSD License
Classifier: Operating System :: OS Independent
Classifier: Intended Audience :: Science/Research
Classifier: Intended Audience :: Developers
Classifier: Intended Audience :: Education
Classifier: Topic :: Text Processing :: Linguistic
Requires-Python: >=3.8
License-File: LICENSE.adoc
Requires-Dist: regex
